{
  "content": [
    {
      "title": "【影片名称】：最新2018网红萝莉嫩妹萌白酱(甜味弥漫)VIP付费作品之白丝护士服 幸福的香蕉速插一线天粉鲍 高清720P完整版【影片大小】：515M【影片时间】：22:32【影片格式】：MP4【是否有码】：无码 【图片预览】：",
      "url": "www.yifile.com/file/U4Lwf3LCmgrVih8Z7mG8.html"
    },
    {
      "title": "=============================================================【影片名称】：风流大神体验小按摩会所黑丝丸子头美女技师的泄火服务价格亲民技术到位按摩胸推臀推毒龙口爆相当卖力720P高清【影片格式】：MP4【影片大小】：350MB【影片时间】：43:04【影片说明】：无码【影片截图】：        【推荐地址】",
      "url": "www.yifile.com/file/UYHwcHrFxljVih8Z7mG/.html"
    },
    {
      "title": "==========================================================================【影片名称】：91罗伊豪华巨献-调操大一双马尾18岁嫩鲍小萝莉 道具大屌强双插调教 后入拽小辫爆操求饶 高清1080P原版无水【影片大小】：1220M【影片时间】：36:11【影片格式】：MP4【是否有码】：无码 【视频背景】：引用:? ???继上次给小妹妹进行道具双插调教后，明显小M爱上了被强行插入的感觉。天天吵着要啪啪啪，还要穿上可爱的衣服。本次拎她好好一顿暴操，从一开始大叫不要，后面慢慢开始大叫不要停。╮(￣▽￣”)╭才上大一，这可让以后的男朋友如何是好哟。本次多视角自拍，完整版高清1080P，36分钟左右,画面高清晰，无任何广告水印。无论从录制画面、女主颜值、拍摄角度等，都不输其他91老干部。  【图片预览】：",
      "url": "www.yifile.com/file/B9T7cnWVwg3Vih8Z7mC9.html"
    },
    {
      "title": "-------------------------------------------------------------------【影片名稱】:刚出来做援交的97年极品性感外围美女看见男的有点胖不是很配合,舔爽后主动要操,瘦小的身材被后插式狂操!【影片大小】: 226MB【影片时间】: 00:11:10【有码无码】: 无码【影图预览】:",
      "url": "www.yifile.com/file/XIbwdyXPlV7Vih8Z7mC+.html"
    },
    {
      "title": "-------------------------------------------------------------------【影片名称】：富商异地游玩高级酒店约战大学生援交妹多体位爆操啊啊大声淫叫把妹纸干的说累死了720P高清【影片格式】：MP4【影片大小】：438MB【影片时间】：42:27【影片说明】：无码【影片截图】：       【推荐地址】：",
      "url": "www.yifile.com/file/VoPxJHTBxV3Vih8Z7mCw.html"
    },
    {
      "title": "-------------------------------------------------------------------【影片名称】：富家公子哥有钱喜好特殊恋丝癖星级酒店约啪学院派极品女神学生妹肉丝足交小穴一摸就出水插入激情啪啪啪【影片格式】：MP4【影片大小】：460MB【影片时间】：15:39【影片说明】：无码【影片截图】：        【推荐地址】",
      "url": "www.yifile.com/file/AtTxdnvOwl7Vih8Z72m6.html"
    },
    {
      "title": "-------------------------------------------------------------------【影片名称】：酒吧搭讪98年170极品长腿黑丝促销员 身材超棒 多姿势暴力抽插 全程浪叫狂差 叫声销魂可射 高清1080P完整版【影片大小】：512M【影片时间】：33:22【影片格式】：MP4【是否有码】：无码【视频背景】：引用:? ???酒吧搭讪98年170酒水黑丝促销员 长相甜美清纯 胸部特别有弹性 最主要的是叫声特别销魂 女人最真实得样子 就是当你鸡巴插入她身体一瞬间的样子 全程浪叫狂插 对了女孩说自己从来没吃过男人鸡巴 嘴是处 当我放进嘴得一瞬间 使劲插她嘴 过瘾死了！   【图片预览】：",
      "url": "www.yifile.com/file/U9P2IyXBmwnVih8Z72mx.html"
    },
    {
      "title": "-------------------------------------------------------------------【影片名称】：网红刘婷精彩演绎女儿在房间睡觉被弄醒和爸爸乱伦呻吟给力对白精彩【影片格式】：MP4【影片大小】：467MB【影片时间】：00:25:03【影片说明】：无码 【影片截图】：",
      "url": "www.yifile.com/file/UYT2cXGSxl/Vih8Z72i+.html"
    },
    {
      "title": "-------------------------------------------------------------------【影片名稱】:德莱文666-极品黑丝大胸翘臀美女太敏感,刚操就高喊:插我,快用力操我,不要停,好多水.最后被干哭了!高清无水印!【影片大小】: 504MB【影片时间】: 01:01:33【有码无码】: 无码【影图预览】:",
      "url": "www.yifile.com/file/AtKhJSLExQnVih8Z72u4.html"
    },
    {
      "title": "-------------------------------------------------------------------【影片名称】：呻吟声听了让人心痒痒想使劲撞她的骚女被抓着头发爆操肥臀说不行了还叫爸爸口活非常赞对白淫荡1080P超清【影片格式】：MP4【影片大小】：284MB【影片时间】：09:48【影片说明】：无码【影片截图】：      【推荐地址】：",
      "url": "www.yifile.com/file/AIShI3LOkFzVih8Z72u7.html"
    },
    {
      "title": "=========================================================================【影片名称】：富家公子有钱玩女神驱车约炮艺术学院气质美女车中就开始搞让做啥就做啥车上自摸宾馆暴力插嘴到干呕插穴呻吟一流对白精彩【影片格式】：MP4【影片大小】：217MB【影片时间】：15:41【影片说明】：无码【影片截图】：           【推荐地址】：",
      "url": "www.yifile.com/file/XdHwJHvFlQrVih8Z72u/.html"
    },
    {
      "title": "-------------------------------------------------------------------【影片名称】：发工资晚上去城中村找了个笑容甜美的少妇站街妹出火1080P高清多角度拍摄【影片格式】：MP4【影片大小】：750MB【影片时间】：00:32:46【影片说明】：无码 【影片截图】：",
      "url": "www.yifile.com/file/VNGhdibBxVzVih8Z72q6.html"
    },
    {
      "title": "-------------------------------------------------------------------【影片名稱】:广东约约哥高级会所约操高颜值极品黑丝大长腿美女,炮椅上搞完又到床上沙发上继续操.相当激烈.高清无水印版!【影片大小】: 861MB【影片时间】: 01:02:41【有码无码】: 无码【影图预览】:",
      "url": "www.yifile.com/file/B4f3fnbGxV7Vih8Z72qx.html"
    },
    {
      "title": "-------------------------------------------------------------------【影片名稱】:天生爱风流精品大作-性感黑丝美女正按摩时突然有急事要先走叫表妹来顶班,美女既性感又漂亮加了500元才让操!【影片大小】: 582MB【影片时间】: 00:19:40【有码无码】: 无码【影图预览】:",
      "url": "www.yifile.com/file/UNagdHrPkF3Vih8Z7226.html"
    },
    {
      "title": "============================================================================【影片名称】：老污龟名作前篇-19岁美腿开档肉丝与疯狂女王上位 爆操无毛嫩逼美鲍超多白浆无套抽插呻吟 高清1080P完整版【影片大小】：357M【影片时间】：23:02【影片格式】：MP4【是否有码】：无码 【图片预览】：",
      "url": "www.yifile.com/file/UNWjJ3KTm13Vih8Z7229.html"
    },
    {
      "title": "-------------------------------------------------------------------【影片名稱】:【真实自拍】-五星级酒店操个气质漂亮的熟女,先口爆再啪啪,快射时女的很吃惊说:啊,你在录像啊!男不承认赶紧走!【影片大小】: 427MB【影片时间】: 00:38:00【有碼無碼】: 无码【影图预览】:",
      "url": "www.yifile.com/file/UdXxJSaSlgrVih8Z722+.html"
    },
    {
      "title": "=====================================================================【影片名稱】:91佛爷又一次微信约操身材苗条奶子超大的漂亮大学美女宾馆啪啪,全程不休息干完又干,奶大逼紧身材好,极品!【影片大小】: 304MB【影片时间】: 00:37:49【有碼無碼】: 无码【影图预览】:",
      "url": "www.yifile.com/file/BYbwIibFmlTVih8Z722w.html"
    },
    {
      "title": "-------------------------------------------------------------------【影片名称】：“不要停不要停”91大神QXS约啪极品大奶子外围女特敏感被搞的各种高潮喷水肏的胡言乱语呻吟不断对白刺激720P【影片格式】：MP4【影片大小】：300MB【影片时间】：31:30【影片说明】：无码【影片截图】：              【推荐地址】：",
      "url": "www.yifile.com/file/Bo73JHvCklXVih8Z72y4.html"
    },
    {
      "title": "-------------------------------------------------------------------【影片名称】：老污龟最新力作-怒操新勾搭的实习空姐 制服开档灰丝无套抽插 白浆四溢 爆操到瘫软淫叫 高清1080P完整版【影片大小】：324M【影片时间】：14:23【影片格式】：MP4【是否有码】：无码 【图片预览】：",
      "url": "www.yifile.com/file/XYanIHSQlFjVih8Z72y6.html"
    },
    {
      "title": "-------------------------------------------------------------------【影片名稱】: 【重磅福利】-气质漂亮的美女人妻公司聚时被同事灌醉带回家中疯狂玩弄后强力抽插,白嫩漂亮超刺激.高清版!【影片大小】: 391MB【影片时间】: 00:17:47【有碼無碼】: 无码【影图预览】:",
      "url": "www.yifile.com/file/UYPzJCaUml7Vih8Z72y7.html"
    },
    {
      "title": "-------------------------------------------------------------------【影片名称】：微信约啪学院派美女援交妹性感黑丝美腿阴毛旺盛轻轻一弄就出水性经验不多安全套都能戴反呻吟好听【影片格式】：MP4【影片大小】：414MB【影片时间】：11:32【影片说明】：无码【影片截图】：           【推荐地址】：",
      "url": "www.yifile.com/file/BobwI3eUxQ/Vih8Z72y9.html"
    },
    {
      "title": "-------------------------------------------------------------------【影片名称】：对白搞笑的贷款潜规则极品骚女KTV包房爆操 黑丝网袜掰开腿暴力抽插720P高清完整版【影片格式】：MP4【影片大小】：993MB【影片时间】：01:05:12【影片说明】：无码 【影片截图】：",
      "url": "www.yifile.com/file/XYChfnuVxV/Vih8Z72+5.html"
    },
    {
      "title": "==============================================================================【影片名稱】:文艺范的漂亮大学美女被厉害的男友操第2次时哀求:不要了,我不行了.接着干第3次.女的特别能叫床!【影片大小】: 690MB【影片时间】: 01:26:51【有码无码】: 无码【影图预览】:",
      "url": "www.yifile.com/file/VNKmcXqXlw7Vih8Z72+8.html"
    },
    {
      "title": "===================================================================【影片名稱】:趁朋友出差约他性感漂亮的女友来家做客,期间不停挑逗终于就范,床上客厅不停爆操,女说:我有点不好意思.国语!【影片大小】: 230MB【影片时间】: 00:10:31【有码无码】: 无码【影图预览】:",
      "url": "www.yifile.com/file/VYXwJXfPk1/Vih8Z72+9.html"
    },
    {
      "title": "=========================================================================【影片名称】：微博极品美乳萝莉美少女柚木人形母犬私拍 淫荡乳夹调教 高清原版私拍39P 超清1080P原版无水印【影片大小】：203M 300M/39P【影片时间】：05:36【影片格式】：MP4【是否有码】：无码 【图片预览】：             【备用网盘】：",
      "url": "www.yifile.com/file/V4DwfyKQkA/Vih8Z72+w.html"
    },
    {
      "title": "=================================================================【影片名称】：PANS模特梦梦无内性感丝袜学生制服教室里大尺度私拍脱光了略微有些羞涩【影片格式】：MP4【影片大小】：314MB【影片时间】：14:03【影片说明】：无码【影片截图】：       【推荐地址】",
      "url": "www.yifile.com/file/B4ejcCLGllzVih8Z72+x.html"
    },
    {
      "title": "==========================================================================【影片名称】：“大哥女人”就这么自信 全身刺青 肉欲交尾 猛肏美乳刺青妹 稻川会大嫂3P篇 高清1080P无水印【影片大小】：265M【影片时间】：33:42【影片格式】：MP4【是否有码】：有码引用:【影片简介】：肉欲に飢えた獣のような全身刺青女！見事なまでの身体を晒して男を貪る。極上の美女が豹変！重厚に描かれた肌は素晴らしいの一言！！ガッツリ刺青を入れたアナーキーな女…セックスも普通じゃ満足出来ないまさにど変態！完成までには長い時間がかかる刺青はそれだけに彼女たちの大切な生きている証…。[直译：肉欲,饥饿的野兽一样全身纹身的女人!漂亮的男人的身体扛到赚取暴利,到处拈花惹草。豹极品美女!厚重,描绘的皮肤是非常优秀的一句话! !又放入刺青的无政府、女人的状态……性爱也不是一般不能满足就是变态!完成之前很长一段时间才能刺青是因此她们活着的重要证……。]【剧情简介】：岛国最大的黑帮稻川会老大不行遇害辞世，其妻美惠子是个全身纹满性感纹身的刚烈女子，虽然有着饥饿野兽般的肉欲性爱欲望，拈花惹草，不过这次美惠子为了社团的荣誉，为了追查丈夫被杀害的真相，用她那全身刺青的性感肉体开始了追查... ... 【图片预览】：            【备用网盘】：",
      "url": "www.yifile.com/file/XIXxJHGUklzVih8Z7264.html"
    },
    {
      "title": "===================================================================【影片名称】：极品爆乳S女神闫盼盼大尺度诱惑 妖精般的身材 靓丽的外表 黑丝爆乳 终极诱惑 高清1080P完整版【影片大小】：434M【影片时间】：19:18【影片格式】：MP4【是否有码】：无码 【图片预览】：             【备用网盘】",
      "url": "www.yifile.com/file/UtXzd3HDm1zVih8Z7265.html"
    },
    {
      "title": "===================================================================【影片名稱】:德莱文666-极品黑丝大胸翘臀美女太敏感,刚操就高喊:插我,快用力操我,不要停,好多水.最后被干哭了!高清无水印!【影片大小】: 504MB【影片时间】: 01:01:33【有码无码】: 无码【影图预览】:",
      "url": "www.yifile.com/file/BdKjdnHFlwnVih8Z7268.html"
    },
    {
      "title": "=========================================================================MISSLEG蜜絲 海外版 鑽石系列N001[63P/225M]",
      "url": "www.yifile.com/file/AoL2JHfClgrVih8Z7269.html"
    },
    {
      "title": "===================================================================【影片名称】：秀人网极品乳神S级模特李梓熙《性感小花猫》惹火大尺度诱惑 敲打美臀 淫荡浪叫 高清1080P诱惑版【影片大小】：171M【影片时间】：07:46【影片格式】：MP4【是否有码】：无码 【图片预览】：",
      "url": "www.yifile.com/file/VNL3cXrOlg3Vih8Z726+.html"
    },
    {
      "title": "===================================================================【影片名称】：91风吟鸟唱最新流出作品 嫩模苏欣冉酒店被摄影师edison玩逼后入翘臀1080P高清【影片大小】：783MB【影片格式】：MP4【影片时间】：51分46",
      "url": "www.yifile.com/file/VYPzdHbElA7Vih8Z726/.html"
    },
    {
      "title": "======================================================================魔鬼身材微博女神隔壁小姐姐最新VIP视图 - 堕落的女教师(36P+5V)",
      "url": "www.yifile.com/file/AYTwfnuVkAnVih8Z726x.html"
    },
    {
      "title": "===================================================================【影片名称】：学院派美女多多宾馆私拍青春学生制服乳房饱满坚挺无毛一线BB粉嫩嫩非常诱人看样子性经验不多套图170P 视频1V【影片格式】：MP4 JPG【影片大小】：310MB【影片时间】：170P 00:15【影片说明】：无码【影片截图】：",
      "url": "www.yifile.com/file/AIXyJHKXm17Vih8Z72G4.html"
    },
    {
      "title": "===================================================================【影片名称】：21岁神似那位奔跑吧女星小恶魔系斯伦达美女大生大量中出第二部 【影片格式】：MP4【影片大小】：574M【影片大小】：13:13【影片说明】：无码【影片截图】：",
      "url": "www.yifile.com/file/B9Wjf3vGwV3Vih8Z72G6.html"
    },
    {
      "title": "===================================================================【影片名稱】：魔鬼身材女神级嫩模大尺度私拍流出[MP4/120MB]【影片格式】：MP4【影片大小】：120MB【影片時間】：00:18:09【影片說明】：無碼【影片截圖】：",
      "url": "www.yifile.com/file/BoH1IHDBm1rVih8Z72G7.html"
    },
    {
      "title": "===================================================================极品身材性感嫩模王雨纯大尺度性感私拍分享",
      "url": "www.yifile.com/file/UdX0cHLGxgnVih8Z72G9.html"
    },
    {
      "title": "===================================================================【影片名称】：网红少女软萌萝莉小仙之猫耳白网袜丁裤小炮机振动流好多白浆[MP4/331MB]【影片大小】：331MB【影片时间】：11:30【影片格式】：MP4【影片说明】：无码【影图预览】：有",
      "url": "www.yifile.com/file/XIf7dSGXwlnVih8Z72G+.html"
    },
    {
      "title": "===================================================================【影片名称】：吐血推荐宇航员摄影大师最新作品极品巨乳高颜值女神小奶油被大鸡巴后入[413MB/MP4]【影片格式】：MP4【影片大小】：413MB【影片时间】：00:04:45【影片说明】：无码 【影片截图】：",
      "url": "www.yifile.com/file/AIegJ3rPl13Vih8Z72G/.html"
    },
    {
      "title": "===================================================================【影片名称】：吐血身材极品白虎外围女和有钱客户沙发各种姿势啪啪[328MB/MP4]【影片格式】：MP4【影片大小】：328MB【影片时间】：00:15:33【影片说明】：无码 【影片截图】：",
      "url": "www.yifile.com/file/ANP1cXfDwgrVih8Z72Gw.html"
    },
    {
      "title": "【影片名称】：极品爆乳女神网红尤物杨晨晨超性感黑丝挑逗诱惑视频流出 高清无水印喷血诱惑S换装套图62P 高清720P无水印版【影片大小】：182M【影片时间】：04:54【影片格式】：MP4【是否有码】：无码 【图片预览】：                                                               【备用网盘】",
      "url": "www.yifile.com/file/B9P0JXuQlF7Vih8Z72Gx.html"
    },
    {
      "title": "=================================================================================【影片名称】：像是以前做过台3个姐妹花少妇约啪刷礼物到位的2位土豪老板干完还聊天问你是哪里的3个半小时超长放送对白精彩【影片格式】：MP4【影片大小】：904MB【影片时间】：03:27:29【影片说明】：无码【影片截图】：  【推荐地址】：",
      "url": "www.yifile.com/file/AdanIiCXlA3Vih8Z72C6.html"
    },
    {
      "title": "===================================================================【影片名称】：呻吟声听了让人心痒痒想使劲撞她的骚女被抓着头发爆操肥臀说不行了还叫爸爸口活非常赞对白淫荡1080P超清【影片格式】：MP4【影片大小】：284MB【影片时间】：09:48【影片说明】：无码【影片截图】：      【推荐地址】：",
      "url": "www.yifile.com/file/U4TxJCfDmg3Vih8Z72C7.html"
    },
    {
      "title": "===================================================================【影片名称】：毛毛比较多的萌妹子黄瓜自慰双洞齐插很是诱惑不要错过【影片格式】：MP4【影片大小】：216MB【影片时间】：00:36:06【影片说明】：无码 【影片截图】：",
      "url": "www.yifile.com/file/VNSgJXrOxg7Vih8Z72C9.html"
    },
    {
      "title": "==========================================================================【影片名称】：91BOSS哥超强企划收藏版-疯狂3P黑丝爆乳丰臀美女内射 玩穴引潮吹 超级3P色即是空 超清1080P原版完整无水印【影片大小】：928M【影片时间】：41:18【影片格式】：MP4【是否有码】：无码【视频背景】：引用:    【关于完整版】：原片共约45分钟、1G、真实超清1080P原版，绝世爆乳3P乱操，非常极品，叫床一绝，绝对的超有价值的收藏版。。。**********************************************************************【关于剧情】：3P黑丝丰臀美女足交内射，超级3P战教你中指玩穴引潮吹看此片涨姿势。完整版45分钟 超长剧情，最高质量 。。。   【图片预览】：",
      "url": "www.yifile.com/file/B9PycCCTkFvVih8Z7Gm6.html"
    },
    {
      "title": "===================================================================【影片名称】：美乳女神2018新版小鸟酱 星奈奈3之情趣白丝蝴蝶结 深喉冰屌 爆乳揉穴娇喘呻吟 高清私拍53P 超清2160P原版【影片大小】：567M【影片时间】：09:48【影片格式】：MP4【是否有码】：无码 【图片预览】：            【备用网盘】：",
      "url": "www.yifile.com/file/B4Ckf3eUxl3Vih8Z7Gm9.html"
    },
    {
      "title": "===================================================================【影片名称】：就没见过这么骚的人妻少妇怀着小宝宝还这样浪身材好奶子大脱光扭臀晃腰各种诱惑动作旁边男的貌似在打飞机【影片格式】：MP4【影片大小】：454MB【影片时间】：20:18【影片说明】：无码【影片截图】：     【推荐地址】",
      "url": "www.yifile.com/file/Uoand3TBkF/Vih8Z7Gm+.html"
    },
    {
      "title": "===========================================================================【影片名稱】:陈永仁-番号E001-超漂亮性感的白嫩气质小少妇脱掉内裤在客厅地上被爆操内射.粉嫩馒头逼.高清完整版!【影片大小】: 559MB【影片时间】: 00:25:26【有码无码】: 无码【影图预览】:",
      "url": "www.yifile.com/file/UI7yJHqUwAjVih8Z7Gm/.html"
    },
    {
      "title": "===================================================================【影片名称】：套房圆床马尾辫高颜值苗条美女大学生靓妹与男友开房造爱女主皮肤光滑白嫩打了好几炮呻吟娇嫩720P高清【影片格式】：MP4【影片大小】：552MB【影片时间】：01:10:00【影片说明】：无码【影片截图】：         【推荐地址】",
      "url": "www.yifile.com/file/B9HydSaUlgrVih8Z7Gmw.html"
    },
    {
      "title": "===================================================================【影片名称】：牙科医院护士美眉和网友去唱K被下药灌倒拔下小内裤玩逼流了好多淫水【影片格式】：MP4【影片大小】：525MB【影片时间】：00:23:22【影片说明】：无码 【影片截图】：",
      "url": "www.yifile.com/file/AISjcCbAxVnVih8Z7Gu5.html"
    },
    {
      "title": "===================================================================【影片名稱】:小胖哥外地出差约了个刚做兼职的良家楼凤美女,先付钱才让操,射完一次不休息还可以继续干.国语!【影片大小】: 493MB【影片时间】: 00:39:42【有码无码】: 无码【影图预览】:",
      "url": "www.yifile.com/file/BY/yJXqXwFzVih8Z7Gq5.html"
    },
    {
      "title": "=============================================================================【影片名称】：『4000人斩』77岁日本富豪离奇之死22岁巨乳嫩妻嫌疑最大 遭泄露曾拍素人AV流出 高清无水印版【影片大小】：678M【影片时间】：58:12【影片格式】：MP4【是否有码】：有码引用: 【事件说明】：     请大家先听我说一个故事，有一位野崎幸助，乃是日本富豪，号称花了30亿睡过4000个女人，有「纪州唐璜」之称，虽然富豪年纪老迈已经77岁，今年2月还是迎娶了第三任妻子 — 22岁的嫩妻S女，结果三个半月后他竟然就暴毙死了！？      富豪死时没穿裤子也无人在旁，体内甚至还有大量兴奋剂，警方不排除他杀可能，第一时间发现尸体的妻子S女成了嫌疑犯而受到注目。有週刊踢爆S女身世令人起疑，毕竟她不仅常沉迷牛郎店，还曾经拍过素人AV，比对脸上特徵被认为就是同一人。      ▼22岁的S女脸蛋姣好，身高约165公分，而且还是个巨乳美女。      据日本《週刊新潮》报导，S女出身北海道，父母从事医疗相关工作，有25岁的姐姐和20岁的弟弟，高中毕业后就读美容专门学校，同学描述她不擅长读书、运动，一头黑长直像乖乖女，但其实喜欢喝酒，私下也沉迷牛郎店。      还有网友起底她曾经拍过AV，经比对后认定就是她本人，AV业者也证实确有此事。      她并非正式出道的女优，骚年一共找到她化名「ゆりか(友梨香)」拍摄的4部片，网友指出她本名叫做须藤早贵，网友更指出她爱钱又爱说谎，拍AV也是因为想赚零用钱。      ▼専門学生(インテリア系) ゆりかちゃん 20歳 マジ軟派、初撮。 922 ナンパTV       究竟，这到底是天意的捉弄，亦或是金钱的诱惑？又或者是冥冥中的因果循环 ?让我们看完片儿继续撸下去…【影片简介】：     街头搭讪到巨乳森林系女孩，她说有半年没有做了！      路上搭讪到一位穿牛仔短外套的S级素人，不过和其它的女孩子不一样，长着蓬松的长发和宽松的长裙，原来是一位森林系女孩啊，当然妹子只是穿着比较自然像是从森里走出来的女生并不住在森林啦，然而和美人聊了会才发现妹子是在学校学习室内装饰专业，原来和森林还是有些关系的（呵呵）         更让人惊喜的是妹子目前是单身状态，半年前因为和前男友的性格不和而导致分手，而在这半年里妹子一直处于禁欲状态，可能今天遇到了不开心的事想要发泄一下，没有过多犹豫就和男生来到了宾馆，脱去宽松的服装没想到展现出了惊人的巨乳，主动地坐上来披头散落的黑发和大肉球一起晃动，只能说今天运气太好撩到了如此尤物。  【图片预览】：",
      "url": "www.yifile.com/file/V9T3IieQll/Vih8Z7Gq6.html"
    },
    {
      "title": "===================================================================【影片名称】：风流大神体验小按摩会所黑丝丸子头美女技师的泄火服务价格亲民技术到位按摩胸推臀推毒龙口爆相当卖力720P高清【影片格式】：MP4【影片大小】：350MB【影片时间】：43:04【影片说明】：无码【影片截图】：        【推荐地址】",
      "url": "www.yifile.com/file/UdbzdHHGx1vVih8Z7Gq7.html"
    },
    {
      "title": "===================================================================【影片名称】：秀人网推女郎超爆乳D奶嫩模凯竹浴室大尺度视频MV超诱惑 水枪激射爆乳淫现 高清1080P完整版【影片大小】：214M【影片时间】：13:53【影片格式】：MP4【是否有码】：无码 【图片预览】：          【备用网盘】：",
      "url": "www.yifile.com/file/U9T3d3KTlFvVih8Z7Gq8.html"
    },
    {
      "title": "===================================================================【影片名称】：极品爆乳女神猫女王的日常情趣吊带黑丝套装 超爆G乳 嫩逼浪穴 极品骚货等大屌爆操 高清私拍17P 高清720P版【影片大小】：232M【影片时间】：10:09【影片格式】：MP4【是否有码】：无码 【图片预览】：        【备用网盘】：",
      "url": "www.yifile.com/file/VNH7JXeSwFvVih8Z7Gq9.html"
    },
    {
      "title": "===================================================================【影片名称】：极品爆乳女神完具美少女 这样的玩具酱高跟丝袜爆乳 你喜欢吗？超级喷血诱惑 想被大J8操了？高清720P完整版【影片大小】：269M【影片时间】：11:47【影片格式】：MP4【是否有码】：无码 【图片预览】：        【备用网盘】：",
      "url": "www.yifile.com/file/Bo77IiHPwVrVih8Z7Gq+.html"
    },
    {
      "title": "===================================================================【影片名称】：唯美口活系列 喜欢的不要错过120【影片格式】：MP4【影片大小】：331.1MB【影片时间】：00:10:51【影片说明】：无码 【影片截图】：",
      "url": "www.yifile.com/file/XNX3dXWSkFTVih8Z7Gq/.html"
    },
    {
      "title": "===================================================================【影片名稱】：魔鬼身材性感女神大尺度诱惑皮革内衣自拍流出[MP4/382MB]【影片格式】：MP4【影片大小】：382MB【影片時間】：00:21:01【影片說明】：無碼【影片截圖】：",
      "url": "www.yifile.com/file/Aob6IiXPk17Vih8Z7Gqw.html"
    },
    {
      "title": "===================================================================【影片名稱】：双马尾网红小美女@甜甜的小奶喵VIP收费自拍[MP4/149MB]【影片格式】：MP4【影片大小】：149MB【影片時間】：00:18:09【影片說明】：無碼【影片截圖】：",
      "url": "www.yifile.com/file/UoTyJHuTwQrVih8Z7Gqx.html"
    },
    {
      "title": "===================================================================【影片名稱】：清纯粉嫩巨乳嫩模大尺度私拍流出[MP4/76MB]【影片格式】：MP4【影片大小】：76MB【影片時間】：00:18:09【影片說明】：無碼【影片截圖】：",
      "url": "www.yifile.com/file/BoCkJyDBxVjVih8Z7G24.html"
    }
  ],
  "title": "[一夜精品] 六月第六季 精品收藏 幸福的香蕉速插一线天粉鲍+双马尾18岁嫩鲍小萝莉 道具大屌强双插调教",
  "text": "【影片名称】：最新2018网红萝莉嫩妹萌白酱(甜味弥漫)VIP付费作品之白丝护士服 幸福的香蕉速插一线天粉鲍 高清720P完整版【影片大小】：515M【影片时间】：22:32【影片格式】：MP4【是否有码】：无码 【图片预览】：              【下载地址】https://www.yifile.com/file/U4Lwf3LCmgrVih8Z7mG8.html=============================================================【影片名称】：风流大神体验小按摩会所黑丝丸子头美女技师的泄火服务价格亲民技术到位按摩胸推臀推毒龙口爆相当卖力720P高清【影片格式】：MP4【影片大小】：350MB【影片时间】：43:04【影片说明】：无码【影片截图】：        【推荐地址】https://www.yifile.com/file/UYHwcHrFxljVih8Z7mG/.html==========================================================================【影片名称】：91罗伊豪华巨献-调操大一双马尾18岁嫩鲍小萝莉 道具大屌强双插调教 后入拽小辫爆操求饶 高清1080P原版无水【影片大小】：1220M【影片时间】：36:11【影片格式】：MP4【是否有码】：无码 【视频背景】：引用:? ???继上次给小妹妹进行道具双插调教后，明显小M爱上了被强行插入的感觉。天天吵着要啪啪啪，还要穿上可爱的衣服。本次拎她好好一顿暴操，从一开始大叫不要，后面慢慢开始大叫不要停。╮(￣▽￣”)╭才上大一，这可让以后的男朋友如何是好哟。本次多视角自拍，完整版高清1080P，36分钟左右,画面高清晰，无任何广告水印。无论从录制画面、女主颜值、拍摄角度等，都不输其他91老干部。  【图片预览】：          【下载地址】：https://www.yifile.com/file/B9T7cnWVwg3Vih8Z7mC9.html-------------------------------------------------------------------【影片名稱】:刚出来做援交的97年极品性感外围美女看见男的有点胖不是很配合,舔爽后主动要操,瘦小的身材被后插式狂操!【影片大小】: 226MB【影片时间】: 00:11:10【有码无码】: 无码【影图预览】:       下载地址:https://www.yifile.com/file/XIbwdyXPlV7Vih8Z7mC+.html-------------------------------------------------------------------【影片名称】：富商异地游玩高级酒店约战大学生援交妹多体位爆操啊啊大声淫叫把妹纸干的说累死了720P高清【影片格式】：MP4【影片大小】：438MB【影片时间】：42:27【影片说明】：无码【影片截图】：       【推荐地址】：https://www.yifile.com/file/VoPxJHTBxV3Vih8Z7mCw.html-------------------------------------------------------------------【影片名称】：富家公子哥有钱喜好特殊恋丝癖星级酒店约啪学院派极品女神学生妹肉丝足交小穴一摸就出水插入激情啪啪啪【影片格式】：MP4【影片大小】：460MB【影片时间】：15:39【影片说明】：无码【影片截图】：        【推荐地址】https://www.yifile.com/file/AtTxdnvOwl7Vih8Z72m6.html-------------------------------------------------------------------【影片名称】：酒吧搭讪98年170极品长腿黑丝促销员 身材超棒 多姿势暴力抽插 全程浪叫狂差 叫声销魂可射 高清1080P完整版【影片大小】：512M【影片时间】：33:22【影片格式】：MP4【是否有码】：无码【视频背景】：引用:? ???酒吧搭讪98年170酒水黑丝促销员 长相甜美清纯 胸部特别有弹性 最主要的是叫声特别销魂 女人最真实得样子 就是当你鸡巴插入她身体一瞬间的样子 全程浪叫狂插 对了女孩说自己从来没吃过男人鸡巴 嘴是处 当我放进嘴得一瞬间 使劲插她嘴 过瘾死了！   【图片预览】：           【下载地址】https://www.yifile.com/file/U9P2IyXBmwnVih8Z72mx.html-------------------------------------------------------------------【影片名称】：网红刘婷精彩演绎女儿在房间睡觉被弄醒和爸爸乱伦呻吟给力对白精彩【影片格式】：MP4【影片大小】：467MB【影片时间】：00:25:03【影片说明】：无码 【影片截图】：    【下載地址】:https://www.yifile.com/file/UYT2cXGSxl/Vih8Z72i+.html-------------------------------------------------------------------【影片名稱】:德莱文666-极品黑丝大胸翘臀美女太敏感,刚操就高喊:插我,快用力操我,不要停,好多水.最后被干哭了!高清无水印!【影片大小】: 504MB【影片时间】: 01:01:33【有码无码】: 无码【影图预览】:            下载地址:https://www.yifile.com/file/AtKhJSLExQnVih8Z72u4.html-------------------------------------------------------------------【影片名称】：呻吟声听了让人心痒痒想使劲撞她的骚女被抓着头发爆操肥臀说不行了还叫爸爸口活非常赞对白淫荡1080P超清【影片格式】：MP4【影片大小】：284MB【影片时间】：09:48【影片说明】：无码【影片截图】：      【推荐地址】：https://www.yifile.com/file/AIShI3LOkFzVih8Z72u7.html=========================================================================【影片名称】：富家公子有钱玩女神驱车约炮艺术学院气质美女车中就开始搞让做啥就做啥车上自摸宾馆暴力插嘴到干呕插穴呻吟一流对白精彩【影片格式】：MP4【影片大小】：217MB【影片时间】：15:41【影片说明】：无码【影片截图】：           【推荐地址】：https://www.yifile.com/file/XdHwJHvFlQrVih8Z72u/.html-------------------------------------------------------------------【影片名称】：发工资晚上去城中村找了个笑容甜美的少妇站街妹出火1080P高清多角度拍摄【影片格式】：MP4【影片大小】：750MB【影片时间】：00:32:46【影片说明】：无码 【影片截图】：         【下載地址】https://www.yifile.com/file/VNGhdibBxVzVih8Z72q6.html-------------------------------------------------------------------【影片名稱】:广东约约哥高级会所约操高颜值极品黑丝大长腿美女,炮椅上搞完又到床上沙发上继续操.相当激烈.高清无水印版!【影片大小】: 861MB【影片时间】: 01:02:41【有码无码】: 无码【影图预览】:            下载地址https://www.yifile.com/file/B4f3fnbGxV7Vih8Z72qx.html-------------------------------------------------------------------【影片名稱】:天生爱风流精品大作-性感黑丝美女正按摩时突然有急事要先走叫表妹来顶班,美女既性感又漂亮加了500元才让操!【影片大小】: 582MB【影片时间】: 00:19:40【有码无码】: 无码【影图预览】:         下载地址:https://www.yifile.com/file/UNagdHrPkF3Vih8Z7226.html============================================================================【影片名称】：老污龟名作前篇-19岁美腿开档肉丝与疯狂女王上位 爆操无毛嫩逼美鲍超多白浆无套抽插呻吟 高清1080P完整版【影片大小】：357M【影片时间】：23:02【影片格式】：MP4【是否有码】：无码 【图片预览】：        【下载地址】：https://www.yifile.com/file/UNWjJ3KTm13Vih8Z7229.html-------------------------------------------------------------------【影片名稱】:【真实自拍】-五星级酒店操个气质漂亮的熟女,先口爆再啪啪,快射时女的很吃惊说:啊,你在录像啊!男不承认赶紧走!【影片大小】: 427MB【影片时间】: 00:38:00【有碼無碼】: 无码【影图预览】:            下载地址:https://www.yifile.com/file/UdXxJSaSlgrVih8Z722+.html=====================================================================【影片名稱】:91佛爷又一次微信约操身材苗条奶子超大的漂亮大学美女宾馆啪啪,全程不休息干完又干,奶大逼紧身材好,极品!【影片大小】: 304MB【影片时间】: 00:37:49【有碼無碼】: 无码【影图预览】:          下载地址:https://www.yifile.com/file/BYbwIibFmlTVih8Z722w.html-------------------------------------------------------------------【影片名称】：“不要停不要停”91大神QXS约啪极品大奶子外围女特敏感被搞的各种高潮喷水肏的胡言乱语呻吟不断对白刺激720P【影片格式】：MP4【影片大小】：300MB【影片时间】：31:30【影片说明】：无码【影片截图】：              【推荐地址】：https://www.yifile.com/file/Bo73JHvCklXVih8Z72y4.html-------------------------------------------------------------------【影片名称】：老污龟最新力作-怒操新勾搭的实习空姐 制服开档灰丝无套抽插 白浆四溢 爆操到瘫软淫叫 高清1080P完整版【影片大小】：324M【影片时间】：14:23【影片格式】：MP4【是否有码】：无码 【图片预览】：          【下载地址】：https://www.yifile.com/file/XYanIHSQlFjVih8Z72y6.html-------------------------------------------------------------------【影片名稱】: 【重磅福利】-气质漂亮的美女人妻公司聚时被同事灌醉带回家中疯狂玩弄后强力抽插,白嫩漂亮超刺激.高清版!【影片大小】: 391MB【影片时间】: 00:17:47【有碼無碼】: 无码【影图预览】:         下载地址https://www.yifile.com/file/UYPzJCaUml7Vih8Z72y7.html-------------------------------------------------------------------【影片名称】：微信约啪学院派美女援交妹性感黑丝美腿阴毛旺盛轻轻一弄就出水性经验不多安全套都能戴反呻吟好听【影片格式】：MP4【影片大小】：414MB【影片时间】：11:32【影片说明】：无码【影片截图】：           【推荐地址】：https://www.yifile.com/file/BobwI3eUxQ/Vih8Z72y9.html-------------------------------------------------------------------【影片名称】：对白搞笑的贷款潜规则极品骚女KTV包房爆操 黑丝网袜掰开腿暴力抽插720P高清完整版【影片格式】：MP4【影片大小】：993MB【影片时间】：01:05:12【影片说明】：无码 【影片截图】：               【下載地址】:https://www.yifile.com/file/XYChfnuVxV/Vih8Z72+5.html==============================================================================【影片名稱】:文艺范的漂亮大学美女被厉害的男友操第2次时哀求:不要了,我不行了.接着干第3次.女的特别能叫床!【影片大小】: 690MB【影片时间】: 01:26:51【有码无码】: 无码【影图预览】:             下载地址: https://www.yifile.com/file/VNKmcXqXlw7Vih8Z72+8.html===================================================================【影片名稱】:趁朋友出差约他性感漂亮的女友来家做客,期间不停挑逗终于就范,床上客厅不停爆操,女说:我有点不好意思.国语!【影片大小】: 230MB【影片时间】: 00:10:31【有码无码】: 无码【影图预览】:        下载地址: https://www.yifile.com/file/VYXwJXfPk1/Vih8Z72+9.html=========================================================================【影片名称】：微博极品美乳萝莉美少女柚木人形母犬私拍 淫荡乳夹调教 高清原版私拍39P 超清1080P原版无水印【影片大小】：203M 300M/39P【影片时间】：05:36【影片格式】：MP4【是否有码】：无码 【图片预览】：             【备用网盘】：https://www.yifile.com/file/V4DwfyKQkA/Vih8Z72+w.html=================================================================【影片名称】：PANS模特梦梦无内性感丝袜学生制服教室里大尺度私拍脱光了略微有些羞涩【影片格式】：MP4【影片大小】：314MB【影片时间】：14:03【影片说明】：无码【影片截图】：       【推荐地址】https://www.yifile.com/file/B4ejcCLGllzVih8Z72+x.html==========================================================================【影片名称】：“大哥女人”就这么自信 全身刺青 肉欲交尾 猛肏美乳刺青妹 稻川会大嫂3P篇 高清1080P无水印【影片大小】：265M【影片时间】：33:42【影片格式】：MP4【是否有码】：有码引用:【影片简介】：肉欲に飢えた獣のような全身刺青女！見事なまでの身体を晒して男を貪る。極上の美女が豹変！重厚に描かれた肌は素晴らしいの一言！！ガッツリ刺青を入れたアナーキーな女…セックスも普通じゃ満足出来ないまさにど変態！完成までには長い時間がかかる刺青はそれだけに彼女たちの大切な生きている証…。[直译：肉欲,饥饿的野兽一样全身纹身的女人!漂亮的男人的身体扛到赚取暴利,到处拈花惹草。豹极品美女!厚重,描绘的皮肤是非常优秀的一句话! !又放入刺青的无政府、女人的状态……性爱也不是一般不能满足就是变态!完成之前很长一段时间才能刺青是因此她们活着的重要证……。]【剧情简介】：岛国最大的黑帮稻川会老大不行遇害辞世，其妻美惠子是个全身纹满性感纹身的刚烈女子，虽然有着饥饿野兽般的肉欲性爱欲望，拈花惹草，不过这次美惠子为了社团的荣誉，为了追查丈夫被杀害的真相，用她那全身刺青的性感肉体开始了追查... ... 【图片预览】：            【备用网盘】：https://www.yifile.com/file/XIXxJHGUklzVih8Z7264.html===================================================================【影片名称】：极品爆乳S女神闫盼盼大尺度诱惑 妖精般的身材 靓丽的外表 黑丝爆乳 终极诱惑 高清1080P完整版【影片大小】：434M【影片时间】：19:18【影片格式】：MP4【是否有码】：无码 【图片预览】：             【备用网盘】https://www.yifile.com/file/UtXzd3HDm1zVih8Z7265.html===================================================================【影片名稱】:德莱文666-极品黑丝大胸翘臀美女太敏感,刚操就高喊:插我,快用力操我,不要停,好多水.最后被干哭了!高清无水印!【影片大小】: 504MB【影片时间】: 01:01:33【有码无码】: 无码【影图预览】:            下载地址: https://www.yifile.com/file/BdKjdnHFlwnVih8Z7268.html=========================================================================MISSLEG蜜絲 海外版 鑽石系列N001[63P/225M]   下载地址：https://www.yifile.com/file/AoL2JHfClgrVih8Z7269.html===================================================================【影片名称】：秀人网极品乳神S级模特李梓熙《性感小花猫》惹火大尺度诱惑 敲打美臀 淫荡浪叫 高清1080P诱惑版【影片大小】：171M【影片时间】：07:46【影片格式】：MP4【是否有码】：无码 【图片预览】：    下载地址：https://www.yifile.com/file/VNL3cXrOlg3Vih8Z726+.html===================================================================【影片名称】：91风吟鸟唱最新流出作品 嫩模苏欣冉酒店被摄影师edison玩逼后入翘臀1080P高清【影片大小】：783MB【影片格式】：MP4【影片时间】：51分46    下载地址：https://www.yifile.com/file/VYPzdHbElA7Vih8Z726/.html======================================================================魔鬼身材微博女神隔壁小姐姐最新VIP视图 - 堕落的女教师(36P+5V)     下载地址：https://www.yifile.com/file/AYTwfnuVkAnVih8Z726x.html===================================================================【影片名称】：学院派美女多多宾馆私拍青春学生制服乳房饱满坚挺无毛一线BB粉嫩嫩非常诱人看样子性经验不多套图170P 视频1V【影片格式】：MP4 JPG【影片大小】：310MB【影片时间】：170P 00:15【影片说明】：无码【影片截图】：    下载地址：https://www.yifile.com/file/AIXyJHKXm17Vih8Z72G4.html===================================================================【影片名称】：21岁神似那位奔跑吧女星小恶魔系斯伦达美女大生大量中出第二部 【影片格式】：MP4【影片大小】：574M【影片大小】：13:13【影片说明】：无码【影片截图】：     下载地址https://www.yifile.com/file/B9Wjf3vGwV3Vih8Z72G6.html===================================================================【影片名稱】：魔鬼身材女神级嫩模大尺度私拍流出[MP4/120MB]【影片格式】：MP4【影片大小】：120MB【影片時間】：00:18:09【影片說明】：無碼【影片截圖】：    下载地址：https://www.yifile.com/file/BoH1IHDBm1rVih8Z72G7.html===================================================================极品身材性感嫩模王雨纯大尺度性感私拍分享    下载地址：https://www.yifile.com/file/UdX0cHLGxgnVih8Z72G9.html===================================================================【影片名称】：网红少女软萌萝莉小仙之猫耳白网袜丁裤小炮机振动流好多白浆[MP4/331MB]【影片大小】：331MB【影片时间】：11:30【影片格式】：MP4【影片说明】：无码【影图预览】：有   下载地址https://www.yifile.com/file/XIf7dSGXwlnVih8Z72G+.html===================================================================【影片名称】：吐血推荐宇航员摄影大师最新作品极品巨乳高颜值女神小奶油被大鸡巴后入[413MB/MP4]【影片格式】：MP4【影片大小】：413MB【影片时间】：00:04:45【影片说明】：无码 【影片截图】：    下载地址：https://www.yifile.com/file/AIegJ3rPl13Vih8Z72G/.html===================================================================【影片名称】：吐血身材极品白虎外围女和有钱客户沙发各种姿势啪啪[328MB/MP4]【影片格式】：MP4【影片大小】：328MB【影片时间】：00:15:33【影片说明】：无码 【影片截图】：      下载地址：https://www.yifile.com/file/ANP1cXfDwgrVih8Z72Gw.html【影片名称】：极品爆乳女神网红尤物杨晨晨超性感黑丝挑逗诱惑视频流出 高清无水印喷血诱惑S换装套图62P 高清720P无水印版【影片大小】：182M【影片时间】：04:54【影片格式】：MP4【是否有码】：无码 【图片预览】：                                                               【备用网盘】https://www.yifile.com/file/B9P0JXuQlF7Vih8Z72Gx.html=================================================================================【影片名称】：像是以前做过台3个姐妹花少妇约啪刷礼物到位的2位土豪老板干完还聊天问你是哪里的3个半小时超长放送对白精彩【影片格式】：MP4【影片大小】：904MB【影片时间】：03:27:29【影片说明】：无码【影片截图】：  【推荐地址】：https://www.yifile.com/file/AdanIiCXlA3Vih8Z72C6.html===================================================================【影片名称】：呻吟声听了让人心痒痒想使劲撞她的骚女被抓着头发爆操肥臀说不行了还叫爸爸口活非常赞对白淫荡1080P超清【影片格式】：MP4【影片大小】：284MB【影片时间】：09:48【影片说明】：无码【影片截图】：      【推荐地址】：https://www.yifile.com/file/U4TxJCfDmg3Vih8Z72C7.html===================================================================【影片名称】：毛毛比较多的萌妹子黄瓜自慰双洞齐插很是诱惑不要错过【影片格式】：MP4【影片大小】：216MB【影片时间】：00:36:06【影片说明】：无码 【影片截图】：    下载地址：https://www.yifile.com/file/VNSgJXrOxg7Vih8Z72C9.html==========================================================================【影片名称】：91BOSS哥超强企划收藏版-疯狂3P黑丝爆乳丰臀美女内射 玩穴引潮吹 超级3P色即是空 超清1080P原版完整无水印【影片大小】：928M【影片时间】：41:18【影片格式】：MP4【是否有码】：无码【视频背景】：引用:    【关于完整版】：原片共约45分钟、1G、真实超清1080P原版，绝世爆乳3P乱操，非常极品，叫床一绝，绝对的超有价值的收藏版。。。**********************************************************************【关于剧情】：3P黑丝丰臀美女足交内射，超级3P战教你中指玩穴引潮吹看此片涨姿势。完整版45分钟 超长剧情，最高质量 。。。   【图片预览】：               【下载地址】：https://www.yifile.com/file/B9PycCCTkFvVih8Z7Gm6.html===================================================================【影片名称】：美乳女神2018新版小鸟酱 星奈奈3之情趣白丝蝴蝶结 深喉冰屌 爆乳揉穴娇喘呻吟 高清私拍53P 超清2160P原版【影片大小】：567M【影片时间】：09:48【影片格式】：MP4【是否有码】：无码 【图片预览】：            【备用网盘】：https://www.yifile.com/file/B4Ckf3eUxl3Vih8Z7Gm9.html===================================================================【影片名称】：就没见过这么骚的人妻少妇怀着小宝宝还这样浪身材好奶子大脱光扭臀晃腰各种诱惑动作旁边男的貌似在打飞机【影片格式】：MP4【影片大小】：454MB【影片时间】：20:18【影片说明】：无码【影片截图】：     【推荐地址】https://www.yifile.com/file/Uoand3TBkF/Vih8Z7Gm+.html===========================================================================【影片名稱】:陈永仁-番号E001-超漂亮性感的白嫩气质小少妇脱掉内裤在客厅地上被爆操内射.粉嫩馒头逼.高清完整版!【影片大小】: 559MB【影片时间】: 00:25:26【有码无码】: 无码【影图预览】:            下载地址:https://www.yifile.com/file/UI7yJHqUwAjVih8Z7Gm/.html===================================================================【影片名称】：套房圆床马尾辫高颜值苗条美女大学生靓妹与男友开房造爱女主皮肤光滑白嫩打了好几炮呻吟娇嫩720P高清【影片格式】：MP4【影片大小】：552MB【影片时间】：01:10:00【影片说明】：无码【影片截图】：         【推荐地址】https://www.yifile.com/file/B9HydSaUlgrVih8Z7Gmw.html===================================================================【影片名称】：牙科医院护士美眉和网友去唱K被下药灌倒拔下小内裤玩逼流了好多淫水【影片格式】：MP4【影片大小】：525MB【影片时间】：00:23:22【影片说明】：无码 【影片截图】：        【下載地址https://www.yifile.com/file/AISjcCbAxVnVih8Z7Gu5.html===================================================================【影片名稱】:小胖哥外地出差约了个刚做兼职的良家楼凤美女,先付钱才让操,射完一次不休息还可以继续干.国语!【影片大小】: 493MB【影片时间】: 00:39:42【有码无码】: 无码【影图预览】:          下载地址: https://www.yifile.com/file/BY/yJXqXwFzVih8Z7Gq5.html=============================================================================【影片名称】：『4000人斩』77岁日本富豪离奇之死22岁巨乳嫩妻嫌疑最大 遭泄露曾拍素人AV流出 高清无水印版【影片大小】：678M【影片时间】：58:12【影片格式】：MP4【是否有码】：有码引用: 【事件说明】：     请大家先听我说一个故事，有一位野崎幸助，乃是日本富豪，号称花了30亿睡过4000个女人，有「纪州唐璜」之称，虽然富豪年纪老迈已经77岁，今年2月还是迎娶了第三任妻子 — 22岁的嫩妻S女，结果三个半月后他竟然就暴毙死了！？      富豪死时没穿裤子也无人在旁，体内甚至还有大量兴奋剂，警方不排除他杀可能，第一时间发现尸体的妻子S女成了嫌疑犯而受到注目。有週刊踢爆S女身世令人起疑，毕竟她不仅常沉迷牛郎店，还曾经拍过素人AV，比对脸上特徵被认为就是同一人。      ▼22岁的S女脸蛋姣好，身高约165公分，而且还是个巨乳美女。      据日本《週刊新潮》报导，S女出身北海道，父母从事医疗相关工作，有25岁的姐姐和20岁的弟弟，高中毕业后就读美容专门学校，同学描述她不擅长读书、运动，一头黑长直像乖乖女，但其实喜欢喝酒，私下也沉迷牛郎店。      还有网友起底她曾经拍过AV，经比对后认定就是她本人，AV业者也证实确有此事。      她并非正式出道的女优，骚年一共找到她化名「ゆりか(友梨香)」拍摄的4部片，网友指出她本名叫做须藤早贵，网友更指出她爱钱又爱说谎，拍AV也是因为想赚零用钱。      ▼専門学生(インテリア系) ゆりかちゃん 20歳 マジ軟派、初撮。 922 ナンパTV       究竟，这到底是天意的捉弄，亦或是金钱的诱惑？又或者是冥冥中的因果循环 ?让我们看完片儿继续撸下去…【影片简介】：     街头搭讪到巨乳森林系女孩，她说有半年没有做了！      路上搭讪到一位穿牛仔短外套的S级素人，不过和其它的女孩子不一样，长着蓬松的长发和宽松的长裙，原来是一位森林系女孩啊，当然妹子只是穿着比较自然像是从森里走出来的女生并不住在森林啦，然而和美人聊了会才发现妹子是在学校学习室内装饰专业，原来和森林还是有些关系的（呵呵）         更让人惊喜的是妹子目前是单身状态，半年前因为和前男友的性格不和而导致分手，而在这半年里妹子一直处于禁欲状态，可能今天遇到了不开心的事想要发泄一下，没有过多犹豫就和男生来到了宾馆，脱去宽松的服装没想到展现出了惊人的巨乳，主动地坐上来披头散落的黑发和大肉球一起晃动，只能说今天运气太好撩到了如此尤物。  【图片预览】：           【下载地址】：https://www.yifile.com/file/V9T3IieQll/Vih8Z7Gq6.html===================================================================【影片名称】：风流大神体验小按摩会所黑丝丸子头美女技师的泄火服务价格亲民技术到位按摩胸推臀推毒龙口爆相当卖力720P高清【影片格式】：MP4【影片大小】：350MB【影片时间】：43:04【影片说明】：无码【影片截图】：        【推荐地址】https://www.yifile.com/file/UdbzdHHGx1vVih8Z7Gq7.html===================================================================【影片名称】：秀人网推女郎超爆乳D奶嫩模凯竹浴室大尺度视频MV超诱惑 水枪激射爆乳淫现 高清1080P完整版【影片大小】：214M【影片时间】：13:53【影片格式】：MP4【是否有码】：无码 【图片预览】：          【备用网盘】：https://www.yifile.com/file/U9T3d3KTlFvVih8Z7Gq8.html===================================================================【影片名称】：极品爆乳女神猫女王的日常情趣吊带黑丝套装 超爆G乳 嫩逼浪穴 极品骚货等大屌爆操 高清私拍17P 高清720P版【影片大小】：232M【影片时间】：10:09【影片格式】：MP4【是否有码】：无码 【图片预览】：        【备用网盘】：https://www.yifile.com/file/VNH7JXeSwFvVih8Z7Gq9.html===================================================================【影片名称】：极品爆乳女神完具美少女 这样的玩具酱高跟丝袜爆乳 你喜欢吗？超级喷血诱惑 想被大J8操了？高清720P完整版【影片大小】：269M【影片时间】：11:47【影片格式】：MP4【是否有码】：无码 【图片预览】：        【备用网盘】：https://www.yifile.com/file/Bo77IiHPwVrVih8Z7Gq+.html===================================================================【影片名称】：唯美口活系列 喜欢的不要错过120【影片格式】：MP4【影片大小】：331.1MB【影片时间】：00:10:51【影片说明】：无码 【影片截图】：    下载地址：https://www.yifile.com/file/XNX3dXWSkFTVih8Z7Gq/.html===================================================================【影片名稱】：魔鬼身材性感女神大尺度诱惑皮革内衣自拍流出[MP4/382MB]【影片格式】：MP4【影片大小】：382MB【影片時間】：00:21:01【影片說明】：無碼【影片截圖】：  下载地址：https://www.yifile.com/file/Aob6IiXPk17Vih8Z7Gqw.html===================================================================【影片名稱】：双马尾网红小美女@甜甜的小奶喵VIP收费自拍[MP4/149MB]【影片格式】：MP4【影片大小】：149MB【影片時間】：00:18:09【影片說明】：無碼【影片截圖】：   下载地址https://www.yifile.com/file/UoTyJHuTwQrVih8Z7Gqx.html===================================================================【影片名稱】：清纯粉嫩巨乳嫩模大尺度私拍流出[MP4/76MB]【影片格式】：MP4【影片大小】：76MB【影片時間】：00:18:09【影片說明】：無碼【影片截圖】：   下载地址https://www.yifile.com/file/BoCkJyDBxVjVih8Z7G24.html资源很丰富，支持10241024感谢分享感谢分享，下载中感谢分享帖子里不能放链接的。资源倒是好资源刚刚撸完一发，补补再下载吧！看看感谢分享10241024感谢分享，资源好多啊，看来不得不办个vip了感谢分享感谢分享感谢分享1024谢谢分享感谢分享。感谢分享谢谢分享谢谢分享"
}